README.md
setup.py
jetkiller/__init__.py
jetkiller/__main__.py
jetkiller/array.py
jetkiller/config.py
jetkiller/file.py
jetkiller/gui.py
jetkiller/image.py
jetkiller.egg-info/PKG-INFO
jetkiller.egg-info/SOURCES.txt
jetkiller.egg-info/dependency_links.txt
jetkiller.egg-info/entry_points.txt
jetkiller.egg-info/requires.txt
jetkiller.egg-info/top_level.txt
tests/__init__.py
tests/test_array.py
tests/test_file.py
tests/test_image.py
tests/test_main.py