Metadata-Version: 2.1
Name: jetkiller
Version: 1.0.0
Summary: Enhance data visualizations using the "jet" colormap.
Home-page: https://github.com/Arnaud-D/jetkiller
Author: Arnaud-D
License: UNKNOWN
Platform: UNKNOWN
Classifier: License :: OSI Approved :: MIT License
